bbrc_bx-0.7.dist-info/licenses/LICENSE
bx/__init__.py
bx/alps.py
bx/ants.py
bx/archiving.py
bx/ashs.py
bx/asl3d.py
bx/bamos.py
bx/basil.py
bx/braak.py
bx/cache.py
bx/cat12.py
bx/cli.py
bx/command.py
bx/dartel.py
bx/dcm.py
bx/donsurf.py
bx/download.py
bx/dtifit.py
bx/dump.py
bx/fmriprep.py
bx/freesurfer.py
bx/id.py
bx/lcmodel.py
bx/lists.py
bx/mrtrix3.py
bx/nifti.py
bx/parse.py
bx/pet.py
bx/qsmxt.py
bx/scandates.py
bx/signature.py
bx/spm12.py
bx/validation.py
bx/xcpd.py
bx/xnat.py
bx/data/logo
bx/data/aal2/AAL2.nii
bx/data/braak/Braak_III_IV.nii.gz
bx/data/braak/Braak_I_II.nii.gz
bx/data/braak/Braak_V_VI.nii.gz
bx/data/dickerson/ad/lh.adsig.annot
bx/data/dickerson/ad/lh.adsig.label
bx/data/dickerson/ad/lh.ag.label
bx/data/dickerson/ad/lh.ifs.label
bx/data/dickerson/ad/lh.itg.label
bx/data/dickerson/ad/lh.mtl.label
bx/data/dickerson/ad/lh.precun.label
bx/data/dickerson/ad/lh.sfg.label
bx/data/dickerson/ad/lh.smg.label
bx/data/dickerson/ad/lh.spl.label
bx/data/dickerson/ad/lh.tpole.label
bx/data/dickerson/ad/readme.txt
bx/data/dickerson/ad/rh.adsig.annot
bx/data/dickerson/ad/rh.adsig.label
bx/data/dickerson/ad/rh.ag.label
bx/data/dickerson/ad/rh.ifs.label
bx/data/dickerson/ad/rh.itg.label
bx/data/dickerson/ad/rh.mtl.label
bx/data/dickerson/ad/rh.precun.label
bx/data/dickerson/ad/rh.sfg.label
bx/data/dickerson/ad/rh.smg.label
bx/data/dickerson/ad/rh.spl.label
bx/data/dickerson/ad/rh.tpole.label
bx/data/dickerson/aging/lh.ag.label
bx/data/dickerson/aging/lh.calcarine.label
bx/data/dickerson/aging/lh.cfusi.label
bx/data/dickerson/aging/lh.cinsula.label
bx/data/dickerson/aging/lh.cmfg.label
bx/data/dickerson/aging/lh.cuneus.label
bx/data/dickerson/aging/lh.ifg.label
bx/data/dickerson/aging/lh.loccip.label
bx/data/dickerson/aging/lh.msfg.label
bx/data/dickerson/aging/lh.precent.label
bx/data/dickerson/aging/lh.smg.label
bx/data/dickerson/aging/rh.ag.label
bx/data/dickerson/aging/rh.calcarine.label
bx/data/dickerson/aging/rh.cfusi.label
bx/data/dickerson/aging/rh.cinsula.label
bbrc_bx-0.7.dist-info/METADATA
bbrc_bx-0.7.dist-info/WHEEL
bbrc_bx-0.7.dist-info/entry_points.txt
bbrc_bx-0.7.dist-info/top_level.txt
bbrc_bx-0.7.dist-info/RECORD
