Metadata-Version: 2.4
Name: bbrc-bx
Version: 0.7
Summary: BarcelonaBeta + XNAT = bx
Home-page: https://gitlab.com/bbrc/xnat/bx
Download-URL: https://gitlab.com/bbrc/xnat/bx/-/archive/v0.7/bx-v0.7.tar.gz
Author: Greg Operto, Jordi Huguet
Author-email: jhuguet@barcelonabeta.org
Classifier: Intended Audience :: Science/Research
Classifier: Intended Audience :: Developers
Classifier: Topic :: Scientific/Engineering
Classifier: Operating System :: OS Independent
Classifier: License :: OSI Approved :: GNU General Public License v3 (GPLv3)
Classifier: Programming Language :: Python :: 3.9
Classifier: Programming Language :: Python :: 3.10
License-File: LICENSE
Requires-Dist: coverage>=4.5
Requires-Dist: pytest>=7.1
Requires-Dist: pytest-cov>=4.0
Requires-Dist: requests>=2.21
Requires-Dist: six>=1.10
Requires-Dist: lxml>=4.3
Requires-Dist: nibabel>=2.3
Requires-Dist: pydicom>=1.2
Requires-Dist: numpy>=1.16
Requires-Dist: pandas>=0.24
Requires-Dist: xlrd>=1.2
Requires-Dist: xlutils>=2.0
Requires-Dist: xlwt>=1.3
Requires-Dist: tqdm>=4.31
Requires-Dist: openpyxl>=2.6
Requires-Dist: bbrc-pyxnat>=1.6.3
Requires-Dist: rich>=10.1
Dynamic: author
Dynamic: author-email
Dynamic: classifier
Dynamic: description
Dynamic: description-content-type
Dynamic: download-url
Dynamic: home-page
Dynamic: license-file
Dynamic: requires-dist
Dynamic: summary
